{
    "title": "ACE 435",
    "names": "Global Agribusiness Management",
    "credit": "3 hours.",
    "intro": "Examination of the economic and strategic management of food, textile, and agribusiness firms within a global business environment; topics include the global business environment and its institutions, organizational strategies and policies, and business operations in global agricultural, food and textile industries. ",
    "instructors": [
        "Kim, C",
        "Irani, K"
    ],
    "prereq": [
        "ACE 231",
        "ACE 222",
        "BADM 320"
    ]
}