{
    "title": "AFRO 100",
    "names": "Intro to African American St",
    "credit": "3 hours.",
    "intro": "Interdisciplinary introduction to the basic concepts and literature in the disciplines covered by African American studies; surveys the major approaches to the study of African Americans across several academic disciplines including economics, education, psychology, literature, political science, sociology and others.",
    "instructors": [
        "Sullers, A",
        "McMillion, D"
    ],
    "prereq": []
}