{
    "title": "CHLH 470",
    "names": "Technology, Health, and Aging",
    "credit": "3 OR 4 hours.",
    "intro": "An undergrad/grad interdisciplinary course that is focused on technology, healthcare, and aging. It is a combination lecture/lab course wherein students learn design and evaluation tools, are part of a project development team, participate in transgenerational learning activities with older adults, and focus on technology design to support healthy aging. ",
    "instructors": [
        "Hale, T"
    ],
    "prereq": []
}