{
    "title": "CI 509",
    "names": "Curriculum Research",
    "credit": "4 hours.",
    "intro": "Reviews the principal methodologies used in research on curriculum problems and guides students through the process of working with data in response to research questions; emphasizes qualitative data collection tools and techniques (e.g., surveys, interviews, observations) as well as various theoretical and methodological approaches (e.g., case study, grounded theory, ethnography); emphasizes conceptual and practical problems. ",
    "instructors": [
        "Nunez Cortez, I"
    ],
    "prereq": []
}