{
    "title": "EPOL 590",
    "names": "Advanced Graduate Seminar",
    "credit": "4 hours.",
    "intro": "Seminar in educational policy studies; sections offered in the following fields: (a) history of education; (b) philosophy of education; (c) comparative education; (d) social foundations of education; (e) philosophy of educational research; and (f) historical methods in education. ",
    "instructors": [
        "Gandhi, R",
        "Castillo, N",
        "Thorstensson Davila, L",
        "Nam, Y",
        "Dyson, A",
        "Kang, H",
        "Getowicz, C",
        "Willis, A"
    ],
    "prereq": []
}