{
    "title": "FR 207",
    "names": "Writing and Grammar Workshop",
    "credit": "3 hours.",
    "intro": "Practice-intensive grammar review and vocabulary-building, with an emphasis on strategies to improve accuracy of, and expressivity in, speaking and writing in French. Grammar textbook supplemented with readings and materials from French and Francophone culture (articles, social media, literary works, films). ",
    "instructors": [
        "Fagyal, Z",
        "Thrasher, T"
    ],
    "prereq": [
        "FR 134",
        "FR 104"
    ]
}