{
    "title": "GWS 370",
    "names": "Queer Theory",
    "credit": "3 hours.",
    "intro": "Traces the development of queer theory as a mode for understanding queer studies methodologies and the changing intellectual landscape of key issues in the field. As part of the course, students will review key concepts and theoretical schools of thought, navigating important debates guiding the field. Theories will engage questions of the social and cultural through topics including race, gender, nation, family, history, identity formation, sexology, the state, and capital. ",
    "instructors": [
        "Tarjanyi, P"
    ],
    "prereq": [
        "GWS 100",
        "GWS 201",
        "GWS 202"
    ]
}