{
    "title": "HIST 277",
    "names": "Encounters in Native America",
    "credit": "3 hours.",
    "intro": "An examination of pivotal events in the history of Native peoples in North America. Students will explore the complexity of encounters between American Indians and others through a focus on key moments. These will include religious encounters, military confrontations, and legal struggles as well as social and artistic interactions. ",
    "instructors": [
        "Lehman, D"
    ],
    "prereq": []
}