{
    "title": "IS 471",
    "names": "Instructional Strategies and Techniques for Information Professionals",
    "credit": "2 TO 4 hours.",
    "intro": "Provides an introduction to learning theories and instructional methods used in a variety of information settings, including libraries, archives, museums, online, and educational environments. Includes an overview of theoretical and applied research and discusses relevant issues and concepts. Students will have an opportunity to design and present an instructional program. ",
    "instructors": [
        "Wong, M",
        "Hensley, M"
    ],
    "prereq": []
}