{
    "title": "MFST 301",
    "names": "Experiential Learning Preparedness & Planning",
    "credit": "1 hours.",
    "intro": "First of a three part \"plan-do-review\" series with the goal of immersing students in a professional metropolitan food and environmental systems-related experience. Students will learn what experiential learning is and what defines the best practices of an experiential learning experience. Students will actively participate in developing their learning experience, including defining what they want to learn and how their learning will be assessed. ",
    "instructors": [
        "Dailey, M"
    ],
    "prereq": []
}