{
    "title": "PATH 545",
    "names": "Vet Diagnostic Path 1",
    "credit": "0 TO 6 hours.",
    "intro": "Instruction in diagnostic pathology for pathology majors. Instruction based on necropsy cases with emphasis on necropsy protocol; sample collection and submission; recognition, description, and interpretation of gross and microscopic lesions; and case diagnosis based on all test results. ",
    "instructors": [
        "Baumgartner, W",
        "Vieson, M",
        "Hsiao, S",
        "Fredrickson, R",
        "Roady, P",
        "Samuelson, J"
    ],
    "prereq": []
}