{
    "title": "VM 635",
    "names": "Veterinary Medical Spanish",
    "credit": "2 hours.",
    "intro": "In this course second year veterinary students will learn basic veterinary Spanish terminology to enable them to communicate effectively with clients. This involves language skills necessary to describe diseases of various animals and discuss treatment options, their benefits and side effects, and cost of treatment with the client. ",
    "instructors": [
        "Davila, J"
    ],
    "prereq": []
}